[
    {
        "model": "get_dest.Dest",
        "pk": 1,
        "fields": {
            "dest_name": "中村記念美術館"
        }
    },
    {
        "model": "get_dest.Dest",
        "pk": 2,
        "fields": {
            "dest_name": "金沢能楽美術館"
        }
    },
    {
        "model": "get_dest.Dest",
        "pk": 3,
        "fields": {
            "dest_name": "金箔工芸館"
        }
    },
    {
        "model": "get_dest.Dest",
        "pk": 4,
        "fields": {
            "dest_name": "２１世紀美術館"
        }
    },
    {
        "model": "get_dest.Dest",
        "pk": 5,
        "fields": {
            "dest_name": "いしかわ生活工芸ミュージアム"
        }
    },
    {
        "model": "get_dest.Dest",
        "pk": 6,
        "fields": {
            "dest_name": "国立工芸館"
        }
    }
]